wavedrom/wavy.v
module wavy(i_clk, o_led);
parameter WIDTH = 8;
input i_clk;
output reg [WIDTH-1:0]o_led;

reg [3:0] led_index;

initial led_index = 0; // Our "state" variable
always @(posedge i_clk) begin
if (led_index >= 4'd13) led_index <=0;
else led_index <= led_index + 1;
end

always @(posedge i_clk) begin
case(led_index) 

4'h0 : o_led <= 8'h01;
4'h1 : o_led <= 8'h02;
4'h2 : o_led <= 8'h04;
4'h3 : o_led <= 8'h08;
4'h4 : o_led <= 8'h10;
4'h5 : o_led <= 8'h20;
4'h6 : o_led <= 8'h40;
4'h7 : o_led <= 8'h80;
4'h8 : o_led <= 8'h40;
4'h9 : o_led <= 8'h20;
4'ha : o_led <= 8'h10;
4'hb : o_led <= 8'h08;
4'hc : o_led <= 8'h04;
4'hd : o_led <= 8'h02;
4'he : o_led <= 8'h01;
default: o_led <= 8'h01;
endcase
end

endmodule

wavedrom/blinkytrace.vcd
$version Generated by VerilatedVcd $end
$date Tue Dec  6 23:15:12 2022
 $end
$timescale   1ps $end

 $scope module TOP $end
  $var wire  1 # i_clk $end
  $var wire  8 $ o_led [7:0] $end
  $scope module wavy $end
   $var wire 32 & WIDTH [31:0] $end
   $var wire  1 # i_clk $end
   $var wire  4 % led_index [3:0] $end
   $var wire  8 $ o_led [7:0] $end
  $upscope $end
 $upscope $end
$enddefinitions $end


#8
0#
b00000000 $
b0000 %
b00000000000000000000000000001000 &
#10
1#
b00000001 $
b0001 %
#15
0#
#18
#20
1#
b00000010 $
b0010 %
#25
0#
#28
#30
1#
b00000100 $
b0011 %
#35
0#
#38
#40
1#
b00001000 $
b0100 %
#45
0#
#48
#50
1#
b00010000 $
b0101 %
#55
0#
#58
#60
1#
b00100000 $
b0110 %
#65
0#
#68
#70
1#
b01000000 $
b0111 %
#75
0#
#78
#80
1#
b10000000 $
b1000 %
#85
0#
#88
#90
1#
b01000000 $
b1001 %
#95
0#
#98
#100
1#
b00100000 $
b1010 %
#105
0#
#108
#110
1#
b00010000 $
b1011 %
#115
0#
#118
#120
1#
b00001000 $
b1100 %
#125
0#
#128
#130
1#
b00000100 $
b1101 %
#135
0#
#138
#140
1#
b00000010 $
b0000 %
#145
0#
#148
#150
1#
b00000001 $
b0001 %
#155
0#
#158
#160
1#
b00000010 $
b0010 %
#165
0#
#168
#170
1#
b00000100 $
b0011 %
#175
0#
#178
#180
1#
b00001000 $
b0100 %
#185
0#
#188
#190
1#
b00010000 $
b0101 %
#195
0#
#198
#200
1#
b00100000 $
b0110 %
#205
0#
#208
#210
1#
b01000000 $
b0111 %
#215
0#
#218
#220
1#
b10000000 $
b1000 %
#225
0#
#228
#230
1#
b01000000 $
b1001 %
#235
0#
#238
#240
1#
b00100000 $
b1010 %
#245
0#
#248
#250
1#
b00010000 $
b1011 %
#255
0#
#258
#260
1#
b00001000 $
b1100 %
#265
0#
#268
#270
1#
b00000100 $
b1101 %
#275
0#
#278
#280
1#
b00000010 $
b0000 %
#285
0#
#288
#290
1#
b00000001 $
b0001 %
#295
0#
#298
#300
1#
b00000010 $
b0010 %
#305
0#
#308
#310
1#
b00000100 $
b0011 %
#315
0#
#318
#320
1#
b00001000 $
b0100 %
#325
0#
#328
#330
1#
b00010000 $
b0101 %
#335
0#
#338
#340
1#
b00100000 $
b0110 %
#345
0#
#348
#350
1#
b01000000 $
b0111 %
#355
0#
#358
#360
1#
b10000000 $
b1000 %
#365
0#
#368
#370
1#
b01000000 $
b1001 %
#375
0#
#378
#380
1#
b00100000 $
b1010 %
#385
0#
#388
#390
1#
b00010000 $
b1011 %
#395
0#
#398
#400
1#
b00001000 $
b1100 %
#405
0#
#408
#410
1#
b00000100 $
b1101 %
#415
0#
#418
#420
1#
b00000010 $
b0000 %
#425
0#
#428
#430
1#
b00000001 $
b0001 %
#435
0#
#438
#440
1#
b00000010 $
b0010 %
#445
0#
#448
#450
1#
b00000100 $
b0011 %
#455
0#
#458
#460
1#
b00001000 $
b0100 %
#465
0#
#468
#470
1#
b00010000 $
b0101 %
#475
0#
#478
#480
1#
b00100000 $
b0110 %
#485
0#
#488
#490
1#
b01000000 $
b0111 %
#495
0#
#498
#500
1#
b10000000 $
b1000 %
#505
0#
#508
#510
1#
b01000000 $
b1001 %
#515
0#
#518
#520
1#
b00100000 $
b1010 %
#525
0#
#528
#530
1#
b00010000 $
b1011 %
#535
0#
#538
#540
1#
b00001000 $
b1100 %
#545
0#
#548
#550
1#
b00000100 $
b1101 %
#555
0#
#558
#560
1#
b00000010 $
b0000 %
#565
0#
#568
#570
1#
b00000001 $
b0001 %
#575
0#
#578
#580
1#
b00000010 $
b0010 %
#585
0#
#588
#590
1#
b00000100 $
b0011 %
#595
0#
#598
#600
1#
b00001000 $
b0100 %
#605
0#
#608
#610
1#
b00010000 $
b0101 %
#615
0#
#618
#620
1#
b00100000 $
b0110 %
#625
0#
#628
#630
1#
b01000000 $
b0111 %
#635
0#
#638
#640
1#
b10000000 $
b1000 %
#645
0#
#648
#650
1#
b01000000 $
b1001 %
#655
0#
#658
#660
1#
b00100000 $
b1010 %
#665
0#
#668
#670
1#
b00010000 $
b1011 %
#675
0#
#678
#680
1#
b00001000 $
b1100 %
#685
0#
#688
#690
1#
b00000100 $
b1101 %
#695
0#
#698
#700
1#
b00000010 $
b0000 %
#705
0#
#708
#710
1#
b00000001 $
b0001 %
#715
0#
#718
#720
1#
b00000010 $
b0010 %
#725
0#
#728
#730
1#
b00000100 $
b0011 %
#735
0#
#738
#740
1#
b00001000 $
b0100 %
#745
0#
#748
#750
1#
b00010000 $
b0101 %
#755
0#
#758
#760
1#
b00100000 $
b0110 %
#765
0#
#768
#770
1#
b01000000 $
b0111 %
#775
0#
#778
#780
1#
b10000000 $
b1000 %
#785
0#
#788
#790
1#
b01000000 $
b1001 %
#795
0#
#798
#800
1#
b00100000 $
b1010 %
#805
0#
#808
#810
1#
b00010000 $
b1011 %
#815
0#
#818
#820
1#
b00001000 $
b1100 %
#825
0#
#828
#830
1#
b00000100 $
b1101 %
#835
0#
#838
#840
1#
b00000010 $
b0000 %
#845
0#
#848
#850
1#
b00000001 $
b0001 %
#855
0#
#858
#860
1#
b00000010 $
b0010 %
#865
0#
#868
#870
1#
b00000100 $
b0011 %
#875
0#
#878
#880
1#
b00001000 $
b0100 %
#885
0#
#888
#890
1#
b00010000 $
b0101 %
#895
0#
#898
#900
1#
b00100000 $
b0110 %
#905
0#
#908
#910
1#
b01000000 $
b0111 %
#915
0#
#918
#920
1#
b10000000 $
b1000 %
#925
0#
#928
#930
1#
b01000000 $
b1001 %
#935
0#
#938
#940
1#
b00100000 $
b1010 %
#945
0#
#948
#950
1#
b00010000 $
b1011 %
#955
0#
#958
#960
1#
b00001000 $
b1100 %
#965
0#
#968
#970
1#
b00000100 $
b1101 %
#975
0#
#978
#980
1#
b00000010 $
b0000 %
#985
0#
#988
#990
1#
b00000001 $
b0001 %
#995
0#
#998
#1000
1#
b00000010 $
b0010 %
